epiclibcpp/epiclib.cp313-win_amd64.pyd
epiclibcpp-0.1.0.dist-info/METADATA
epiclibcpp-0.1.0.dist-info/WHEEL
epiclibcpp-0.1.0.dist-info/licenses/LICENSE
epiclibcpp-0.1.0.dist-info/RECORD
