Metadata-Version: 2.2
Name: epiclibcpp
Version: 0.1.0
Summary: EPIC cognitive architecture C++ core exposed as a Python module via pybind11
Author: Travis Seymour
License:                     GNU GENERAL PUBLIC LICENSE
Classifier: Programming Language :: Python :: 3
Classifier: Programming Language :: Python :: 3 :: Only
Classifier: Programming Language :: Python :: 3.10
Classifier: Programming Language :: Python :: 3.11
Classifier: Programming Language :: Python :: 3.12
Classifier: Programming Language :: Python :: 3.13
Classifier: Programming Language :: C++
Classifier: License :: OSI Approved :: GNU General Public License v3 (GPLv3)
Classifier: Operating System :: OS Independent
Project-URL: Homepage, https://github.com/travisseymour/epiclibcpp
Project-URL: Issues, https://github.com/travisseymour/epiclibcpp/issues
Requires-Python: >=3.10
